certbot_deployer_bigip/__init__.py
certbot_deployer_bigip/__main__.py
certbot_deployer_bigip/meta.py
certbot_deployer_bigip/_main/__init__.py
certbot_deployer_bigip/certbot_deployer_bigip/__init__.py
certbot_deployer_bigip-1.1.1.dist-info/licenses/LICENSE
certbot_deployer_bigip-1.1.1.dist-info/METADATA
certbot_deployer_bigip-1.1.1.dist-info/WHEEL
certbot_deployer_bigip-1.1.1.dist-info/entry_points.txt
certbot_deployer_bigip-1.1.1.dist-info/top_level.txt
certbot_deployer_bigip-1.1.1.dist-info/RECORD
