Metadata-Version: 2.4
Name: certbot_deployer_bigip
Version: 1.1.1
Summary: Certbot Deployer plugin for deploying certificates to F5 BIG-IP devices
Home-page: https://github.com/theias/certbot_deployer_bigip
Author: IAS
Author-email: network@ias.edu
Project-URL: Documentation, https://theias.github.io/certbot_deployer_bigip/
Project-URL: Bug Tracker, https://github.com/theias/certbot_deployer_bigip/issues
Project-URL: Source, https://github.com/theias/certbot_deployer_bigip
Classifier: Programming Language :: Python :: 3
Classifier: License :: OSI Approved :: MIT License
Classifier: Operating System :: OS Independent
Requires-Python: >=3.9
License-File: LICENSE
Requires-Dist: certbot_deployer<3.0.0,>=2.0.0
Requires-Dist: cryptography<45.0.0,>=44.0.1
Requires-Dist: fabric<4.0.0,>=3.2.2
Requires-Dist: scp==0.15.0
Dynamic: license-file
